pydantic_api/__init__.py
pydantic_api/base.py
pydantic_api/notion/__init__.py
pydantic_api/notion/api/__init__.py
pydantic_api/notion/api/base.py
pydantic_api/notion/api/blocks.py
pydantic_api/notion/api/comments.py
pydantic_api/notion/api/databases.py
pydantic_api/notion/api/pages.py
pydantic_api/notion/api/search.py
pydantic_api/notion/api/users.py
pydantic_api/notion/entities/__init__.py
pydantic_api/notion/entities/block/__init__.py
pydantic_api/notion/entities/block/rich_text/__init__.py
pydantic_api/notion/entities/block/rich_text/base.py
pydantic_api/notion/entities/block/rich_text/equation.py
pydantic_api/notion/entities/block/rich_text/mention.py
pydantic_api/notion/entities/block/rich_text/rich_text.py
pydantic_api/notion/entities/block/rich_text/text.py
pydantic_api/notion/entities/comment.py
pydantic_api/notion/entities/common.py
pydantic_api/notion/entities/database.py
pydantic_api/notion/entities/emoji.py
pydantic_api/notion/entities/file.py
pydantic_api/notion/entities/link_preview.py
pydantic_api/notion/entities/page.py
pydantic_api/notion/entities/parent.py
pydantic_api/notion/entities/properties/__init__.py
pydantic_api/notion/entities/properties/common.py
pydantic_api/notion/entities/properties/database_property.py
pydantic_api/notion/entities/properties/page_property.py
pydantic_api/notion/entities/user.py
pydantic_notion-0.1.0.dist-info/LICENSE
pydantic_notion-0.1.0.dist-info/METADATA
pydantic_notion-0.1.0.dist-info/WHEEL
pydantic_notion-0.1.0.dist-info/RECORD
